py_avro_schema/__init__.py
py_avro_schema/_schemas.py
py_avro_schema/_testing.py
py_avro_schema/_typing.py
py_avro_schema/py.typed
py_avro_schema-3.8.2.dist-info/LICENSE
py_avro_schema-3.8.2.dist-info/LICENSE_HEADER.txt
py_avro_schema-3.8.2.dist-info/METADATA
py_avro_schema-3.8.2.dist-info/WHEEL
py_avro_schema-3.8.2.dist-info/top_level.txt
py_avro_schema-3.8.2.dist-info/RECORD
