Metadata-Version: 2.1
Name: py-avro-schema
Version: 3.8.2
Summary: Generate Apache Avro schemas for Python types including standard library data-classes and Pydantic data models.
Author-email: "J.P. Morgan Chase & Co." <open_source@jpmorgan.com>
License: Apache License
Project-URL: Homepage, https://github.com/jpmorganchase/py-avro-schema
Project-URL: Bug Tracker, https://github.com/jpmorganchase/py-avro-schema/issues
Project-URL: Documentation, https://py-avro-schema.readthedocs.io
Project-URL: Download, https://pypi.python.org/pypi/py-avro-schema
Project-URL: Source Code, https://github.com/jpmorganchase/py-avro-schema
Keywords: avro,data,dataclasses,deserialization,generate,jpmorganchase,kafka,messaging,pydantic,python,schema,serialization,types
Classifier: Development Status :: 5 - Production/Stable
Classifier: License :: OSI Approved :: Apache Software License
Classifier: Operating System :: OS Independent
Classifier: Programming Language :: Python :: 3
Classifier: Typing :: Typed
Requires-Python: >=3.9
License-File: LICENSE
License-File: LICENSE_HEADER.txt
Requires-Dist: avro~=1.10
Requires-Dist: memoization~=0.4
Requires-Dist: more-itertools~=10.0
Requires-Dist: orjson~=3.5
Requires-Dist: typeguard~=4.0
Provides-Extra: docs
Requires-Dist: sphinx; extra == "docs"
Requires-Dist: sphinx-rtd-theme; extra == "docs"
Provides-Extra: linting
Requires-Dist: black; extra == "linting"
Requires-Dist: flake8; extra == "linting"
Requires-Dist: interrogate; extra == "linting"
Requires-Dist: isort; extra == "linting"
Requires-Dist: mypy; extra == "linting"
Requires-Dist: pre-commit; extra == "linting"
Requires-Dist: pydantic>=2; extra == "linting"
Provides-Extra: testing
Requires-Dist: packaging; extra == "testing"
Requires-Dist: pydantic>=2; extra == "testing"
Requires-Dist: pytest; extra == "testing"
Requires-Dist: pytest-cov; extra == "testing"
